fluctus/__init__.py
fluctus/bootstrap.py
fluctus/hrf.py
fluctus/interfaces.py
fluctus/preprocessing.py
fluctus/viz.py
fluctus-0.0.1.dist-info/METADATA
fluctus-0.0.1.dist-info/WHEEL
fluctus-0.0.1.dist-info/entry_points.txt
fluctus-0.0.1.dist-info/license_files/LICENSE-APACHE
fluctus-0.0.1.dist-info/license_files/LICENSE-MIT
fluctus-0.0.1.dist-info/RECORD
