Metadata-Version: 2.1
Name: fluctus
Version: 0.0.1
Summary: Interface for handling oscillatory data
Requires-Python: >=3.7
